loudness.cpython-313-x86_64-linux-musl.so
loudness.libs/libgcc_s-0cd532bd.so.1
loudness.libs/libstdc++-5d72f927.so.6.0.33
loudness-0.2.0.dist-info/METADATA
loudness-0.2.0.dist-info/WHEEL
loudness-0.2.0.dist-info/RECORD
loudness-0.2.0.dist-info/licenses/LICENSE
loudness-0.2.0.dist-info/sboms/auditwheel.cdx.json
