Metadata-Version: 2.2
Name: loudness
Version: 0.2.0
Summary: Python bindings for libloudness, for calculating integrated loudness in LUFS (ITU BS.1770 / EBU R 128)
Author: Magnus Bro Kolstø, Iver Jordal
License: MIT
Project-URL: Homepage, https://github.com/iver56/loudness
Requires-Python: >=3.10
Requires-Dist: numpy<3,>=1.22
